django_project_panel/__init__.py
django_project_panel/admin.py
django_project_panel/apps.py
django_project_panel/models.py
django_project_panel/project_panel.py
django_project_panel/urls.py
django_project_panel/views.py
django_project_panel/templates/project_panel/clean_table.html
django_project_panel/templates/project_panel/panel.html
django_project_panel-0.0.10.dist-info/METADATA
django_project_panel-0.0.10.dist-info/WHEEL
django_project_panel-0.0.10.dist-info/top_level.txt
django_project_panel-0.0.10.dist-info/RECORD
