Metadata-Version: 2.1
Name: django-project-panel
Version: 0.0.10
Summary: Простая мониторинг-панель проекта (размеры всех таблиц в базе данных, медиа файлов и т.д)
Home-page: https://github.com/EfrosiniaPetrovna/django-project-panel
Author: EfrosiniaPetrovna
Author-email: je.to.prace@gmail.com
Classifier: Programming Language :: Python :: 3.10
Classifier: License :: OSI Approved :: MIT License
Classifier: Operating System :: OS Independent
Classifier: Framework :: Django
Requires-Python: >=3.6
Requires-Dist: psutil (>=5.9.5)
